drivee_client/__init__.py
drivee_client/drivee_client.py
drivee_client/dtos/__init__.py
drivee_client/dtos/base_dto.py
drivee_client/dtos/charge_point_dto.py
drivee_client/dtos/charging_history_dto.py
drivee_client/dtos/charging_period_dto.py
drivee_client/dtos/charging_responses_dto.py
drivee_client/dtos/charging_session_dto.py
drivee_client/dtos/connector_dto.py
drivee_client/dtos/currency_dto.py
drivee_client/dtos/evse_dto.py
drivee_client/dtos/payment_details_dto.py
drivee_client/dtos/power_stats_dto.py
drivee_client/dtos/price_periods_dto.py
drivee_client/errors/__init__.py
drivee_client/models/__init__.py
drivee_client/models/base_model.py
drivee_client/models/charge_point.py
drivee_client/models/charging_history.py
drivee_client/models/charging_response.py
drivee_client/models/charging_session.py
drivee_client/models/connector.py
drivee_client/models/currency.py
drivee_client/models/evse.py
drivee_client/models/power_stats.py
drivee_client/models/power_stats_history_entry.py
drivee_client/models/price_periods.py
drivee_client/models/types.py
driveeclient-0.1.4.dist-info/licenses/LICENSE
driveeclient-0.1.4.dist-info/METADATA
driveeclient-0.1.4.dist-info/WHEEL
driveeclient-0.1.4.dist-info/top_level.txt
driveeclient-0.1.4.dist-info/RECORD
